notedrive/__init__.py
notedrive/baidu/__init__.py
notedrive/baidu/drive.py
notedrive/baidu/token_.py
notedrive/base/__init__.py
notedrive/base/core.py
notedrive/command/__init__.py
notedrive/command/pywget.py
notedrive/filesystem/__init__.py
notedrive/filesystem/base.py
notedrive/lanzou/__init__.py
notedrive/lanzou/drive.py
notedrive/m3u8/__init__.py
notedrive/m3u8/download.py
notedrive/m3u8/mixins.py
notedrive/m3u8/parser.py
notedrive/m3u8/protocol.py
notedrive/others/__init__.py
notedrive/others/aria2/Aria2JsonRpc.py
notedrive/others/aria2/__init__.py
notedrive/others/aria2/a2jrg-scrape.py
notedrive/others/aria2/a2jrg.py
notedrive/others/cache/__init__.py
notedrive/others/cache/load.py
notedrive/others/github/__init__.py
notedrive/others/github/utils.py
notedrive/others/magnet/__init__.py
notedrive/others/magnet/__main__.py
notedrive/others/magnet/core.py
notedrive/others/magnet/peer.py
notedrive/others/magnet/peer_tracker.py
notedrive/others/magnet/server.py
notedrive/others/magnet/settings.py
notedrive/others/magnet/start.py
notedrive/others/magnet/utils.py
notedrive/others/magnet/dht/__init__.py
notedrive/others/magnet/dht/bencode.py
notedrive/others/magnet/dht/core.py
notedrive/others/magnet/dht/core1.py
notedrive/others/magnet/dht/core2.py
notedrive/others/magnet/dht/crawling.py
notedrive/others/magnet/dht/network.py
notedrive/others/magnet/dht/node.py
notedrive/others/magnet/dht/protocol.py
notedrive/others/magnet/dht/routing.py
notedrive/others/magnet/dht/temp1.py
notedrive/others/magnet/dht/torrent.py
notedrive/others/magnet/dht/utils.py
notedrive/sqlalchemy/__init__.py
notedrive/sqlalchemy/base.py
notedrive/tables/__init__.py
notedrive/tables/core.py
notedrive/tables/field.py
notedrive/useless/__init__.py
notedrive/useless/core.py
notedrive/useless/utils.py
notedrive/utils/__init__.py
notedrive/utils/download.py
notedrive-0.6.27.dist-info/LICENSE
notedrive-0.6.27.dist-info/METADATA
notedrive-0.6.27.dist-info/WHEEL
notedrive-0.6.27.dist-info/top_level.txt
notedrive-0.6.27.dist-info/RECORD
