Metadata-Version: 2.1
Name: notedrive
Version: 0.6.27
Summary: notedrive
Home-page: https://github.com/1007530194
Author: niuliangtao
Author-email: 1007530194@qq.com
License-File: LICENSE
Requires-Dist: requests
Requires-Dist: notesecret
Requires-Dist: demjson
Requires-Dist: tqdm
Requires-Dist: requests-toolbelt
Requires-Dist: lanzou-api
